iregex/__init__.py
iregex/consts.py
iregex/exceptions.py
iregex/regex.py
iregex/tests/test_regex_format.py
iregex/tests/test_regex_results.py
iregex-0.2.1.dist-info/WHEEL
iregex-0.2.1.dist-info/METADATA
iregex-0.2.1.dist-info/RECORD
